opto.py
opto-0.1.dist-info/DESCRIPTION.rst
opto-0.1.dist-info/METADATA
opto-0.1.dist-info/RECORD
opto-0.1.dist-info/WHEEL
opto-0.1.dist-info/metadata.json
opto-0.1.dist-info/top_level.txt
