Metadata-Version: 2.0
Name: opto
Version: 0.1
Summary: Python interface to Optotune focus-tunable lenses
Home-page: https://github.com/OrganicIrradiation/opto
Author: Steven A. Cholewiak
Author-email: steven@cholewiak.com
License: MIT
Download-URL: https://github.com/OrganicIrradiation/opto/tarball/v0.1
Keywords: Optotune,optics,lens
Platform: UNKNOWN
Classifier: Development Status :: 3 - Alpha
Classifier: Intended Audience :: Developers
Classifier: Natural Language :: English
Classifier: Operating System :: OS Independent
Classifier: Programming Language :: Python :: 3
Classifier: Topic :: Software Development :: Libraries :: Python Modules
Requires-Dist: pyserial
